Metadata-Version: 1.1
Name: adidentifier
Version: 0.0.8
Summary: AdIdentifier
Home-page: https://github.com/Alecyrus/AdIdentifier
Author: Alecyrus
Author-email: heyuangunia@gmail.com
License: MIT
Platform: UNKNOWN
Classifier: Environment :: Web Environment
Classifier: Intended Audience :: Developers
Classifier: Operating System :: OS Independent
Classifier: Topic :: Text Processing :: Indexing
Classifier: Topic :: Utilities
Classifier: Topic :: Internet
Classifier: Topic :: Software Development :: Libraries :: Python Modules
Classifier: Programming Language :: Python
Classifier: Programming Language :: Python :: 2
Classifier: Programming Language :: Python :: 2.7
